{"match_id":"39d951a395f1485b","date":"2026-07-05","group":null,"stage":"Round of 16","home":"Brazil","away":"Norway","home_code":"brazil","away_code":"norway","status":"scheduled","neutral":true,"city":"East Rutherford","country":"United States","home_score":null,"away_score":null,"prediction":{"prediction_id":"5505e9b31266e84b","match_id":"39d951a395f1485b","model_version_id":"production_ensemble-664b3d0ec7","data_cutoff":"2026-07-03","created_at":"2026-07-04T08:41:01.752258+00:00","date":"2026-07-05","home_team":"Brazil","away_team":"Norway","home_win_probability":0.6032,"draw_probability":0.2573,"away_win_probability":0.1395,"expected_home_goals":1.918,"expected_away_goals":1.174,"expected_total_goals":3.093,"most_likely_score":"1-1","over_2_5":0.5971,"btts_yes":0.5924,"btts_no":0.4076,"over_under":{"0.5":0.9505,"1.5":0.8181,"2.5":0.5971,"3.5":0.3735},"total_goals_dist":[0.0495,0.1324,0.221,0.2236,0.1729,0.107,0.0936],"home_clean_sheet":0.3101,"away_clean_sheet":0.1469,"home_win_to_nil":0.2606,"away_win_to_nil":0.0975,"top_scorelines":[{"score":"1-1","prob":0.106},{"score":"2-1","prob":0.0978},{"score":"2-0","prob":0.0838},{"score":"1-0","prob":0.0832},{"score":"3-1","prob":0.0625},{"score":"1-2","prob":0.0599}],"scorers":[{"player":"Vinícius Júnior","team":"Brazil","prob":0.2805},{"player":"Raphinha","team":"Brazil","prob":0.1824},{"player":"Neymar","team":"Brazil","prob":0.1681},{"player":"Matheus Cunha","team":"Brazil","prob":0.1545},{"player":"Lucas Paquetá","team":"Brazil","prob":0.1293},{"player":"Richarlison","team":"Brazil","prob":0.1234},{"player":"Casemiro","team":"Brazil","prob":0.0828},{"player":"Rodrygo","team":"Brazil","prob":0.0787},{"player":"Gabriel Martinelli","team":"Brazil","prob":0.0652},{"player":"Luiz Henrique","team":"Brazil","prob":0.0548},{"player":"Erling Haaland","team":"Norway","prob":0.4329},{"player":"Alexander Sørloth","team":"Norway","prob":0.1473},{"player":"Thelo Aasgaard","team":"Norway","prob":0.0908},{"player":"Antonio Nusa","team":"Norway","prob":0.0837},{"player":"Mohamed Elyounoussi","team":"Norway","prob":0.0281},{"player":"Felix Horn Myhre","team":"Norway","prob":0.0269},{"player":"Jørgen Strand Larsen","team":"Norway","prob":0.0254},{"player":"Martin Ødegaard","team":"Norway","prob":0.0241},{"player":"Aron Dønnum","team":"Norway","prob":0.0227}],"factors":{"expected_home_goals":1.92,"expected_away_goals":1.17,"neutral_venue":true,"home_is_host":false,"away_is_host":false,"elo_home":2043.4,"elo_away":1911.0,"elo_diff":132.3},"is_frozen":true,"status":"scheduled","home_score":null,"away_score":null}}