{"match_id":"9105a1099c143cee","date":"2026-06-20","group":"E","stage":null,"home":"Germany","away":"Ivory Coast","home_code":"germany","away_code":"ivory-coast","status":"played","neutral":true,"city":"Toronto","country":"Canada","home_score":2,"away_score":1,"prediction":{"prediction_id":"7603df0e1ea0d52c","match_id":"9105a1099c143cee","model_version_id":"production_ensemble-f6dead0608","data_cutoff":"2026-06-19","created_at":"2026-06-30T09:35:55.851679+00:00","date":"2026-06-20","home_team":"Germany","away_team":"Ivory Coast","home_win_probability":0.6358,"draw_probability":0.2776,"away_win_probability":0.0867,"expected_home_goals":1.655,"expected_away_goals":0.907,"expected_total_goals":2.562,"most_likely_score":"1-0","over_2_5":0.4716,"btts_yes":0.4863,"btts_no":0.5137,"over_under":{"0.5":0.9178,"1.5":0.7287,"2.5":0.4716,"3.5":0.256},"total_goals_dist":[0.0822,0.1891,0.2572,0.2155,0.1382,0.071,0.0468],"home_clean_sheet":0.4044,"away_clean_sheet":0.1915,"home_win_to_nil":0.3222,"away_win_to_nil":0.1093,"top_scorelines":[{"score":"1-0","prob":0.1236},{"score":"1-1","prob":0.1199},{"score":"2-0","prob":0.1056},{"score":"2-1","prob":0.0955},{"score":"0-0","prob":0.0822},{"score":"0-1","prob":0.0655}],"scorers":[],"factors":{"expected_home_goals":1.65,"expected_away_goals":0.91,"neutral_venue":true,"home_is_host":false,"away_is_host":false,"elo_home":1963.2,"elo_away":1803.2,"elo_diff":160.0},"is_frozen":true,"status":"played","home_score":2,"away_score":1}}