{"match_id":"943a8bb72de13d0b","date":"2026-06-29","group":null,"stage":"Round of 32","home":"Germany","away":"Paraguay","home_code":"germany","away_code":"paraguay","status":"played","neutral":true,"city":"Foxborough","country":"United States","home_score":1,"away_score":1,"prediction":{"prediction_id":"573c3060646179c9","match_id":"943a8bb72de13d0b","model_version_id":"production_ensemble-0d26706c9d","data_cutoff":"2026-06-28","created_at":"2026-07-10T09:37:22.373009+00:00","date":"2026-06-29","home_team":"Germany","away_team":"Paraguay","home_win_probability":0.6359,"draw_probability":0.2803,"away_win_probability":0.0838,"expected_home_goals":1.66,"expected_away_goals":0.924,"expected_total_goals":2.584,"most_likely_score":"1-0","over_2_5":0.4773,"btts_yes":0.4908,"btts_no":0.5092,"over_under":{"0.5":0.92,"1.5":0.7335,"2.5":0.4773,"3.5":0.2605},"total_goals_dist":[0.08,0.1865,0.2562,0.2168,0.1401,0.0724,0.048],"home_clean_sheet":0.3989,"away_clean_sheet":0.1903,"home_win_to_nil":0.3189,"away_win_to_nil":0.1103,"top_scorelines":[{"score":"1-0","prob":0.1214},{"score":"1-1","prob":0.1195},{"score":"2-0","prob":0.1045},{"score":"2-1","prob":0.0955},{"score":"0-0","prob":0.08},{"score":"0-1","prob":0.0651}],"scorers":[],"factors":{"expected_home_goals":1.66,"expected_away_goals":0.92,"neutral_venue":true,"home_is_host":false,"away_is_host":false,"elo_home":1950.1,"elo_away":1830.3,"elo_diff":119.9},"is_frozen":true,"status":"played","home_score":1,"away_score":1}}