{"match_id":"c205821ce858a15b","date":"2026-06-30","group":"E","home":"Ivory Coast","away":"Norway","status":"scheduled","neutral":true,"city":"Arlington","country":"United States","home_score":null,"away_score":null,"prediction":{"prediction_id":"9fb9df2b1c41cfa4","match_id":"c205821ce858a15b","model_version_id":"production_ensemble-0799f8ebdc","data_cutoff":"2026-06-27","created_at":"2026-06-28T10:29:58.460744+00:00","date":"2026-06-30","home_team":"Ivory Coast","away_team":"Norway","home_win_probability":0.2216,"draw_probability":0.3098,"away_win_probability":0.4685,"expected_home_goals":1.004,"expected_away_goals":1.545,"expected_total_goals":2.549,"most_likely_score":"1-1","over_2_5":0.4659,"btts_yes":0.4996,"btts_no":0.5004,"over_under":{"0.5":0.9132,"1.5":0.7216,"2.5":0.4659,"3.5":0.2546},"total_goals_dist":[0.0868,0.1915,0.2558,0.2112,0.1354,0.0705,0.0487],"home_clean_sheet":0.2202,"away_clean_sheet":0.3671,"home_win_to_nil":0.1334,"away_win_to_nil":0.2803,"top_scorelines":[{"score":"1-1","prob":0.1249},{"score":"0-1","prob":0.1156},{"score":"1-2","prob":0.0912},{"score":"0-2","prob":0.0908},{"score":"0-0","prob":0.0868},{"score":"1-0","prob":0.076}],"scorers":[{"player":"Amad Diallo","team":"Ivory Coast","prob":0.1145},{"player":"Franck Kessié","team":"Ivory Coast","prob":0.1092},{"player":"Sébastien Haller","team":"Ivory Coast","prob":0.0794},{"player":"Nicolas Pépé","team":"Ivory Coast","prob":0.075},{"player":"Yan Diomande","team":"Ivory Coast","prob":0.0668},{"player":"Evann Guessand","team":"Ivory Coast","prob":0.0636},{"player":"Seko Fofana","team":"Ivory Coast","prob":0.0541},{"player":"Jean-Philippe Krasso","team":"Ivory Coast","prob":0.0497},{"player":"Ibrahim Sangaré","team":"Ivory Coast","prob":0.0496},{"player":"Simon Adingra","team":"Ivory Coast","prob":0.0485},{"player":"Erling Haaland","team":"Norway","prob":0.5255},{"player":"Alexander Sørloth","team":"Norway","prob":0.195},{"player":"Thelo Aasgaard","team":"Norway","prob":0.1216},{"player":"Antonio Nusa","team":"Norway","prob":0.0883},{"player":"Mohamed Elyounoussi","team":"Norway","prob":0.0381},{"player":"Felix Horn Myhre","team":"Norway","prob":0.0364},{"player":"Jørgen Strand Larsen","team":"Norway","prob":0.0344},{"player":"Martin Ødegaard","team":"Norway","prob":0.0327},{"player":"Aron Dønnum","team":"Norway","prob":0.0308},{"player":"Marcus Holmgren Pedersen","team":"Norway","prob":0.026}],"factors":{"expected_home_goals":1.0,"expected_away_goals":1.55,"neutral_venue":true,"home_is_host":false,"away_is_host":false,"elo_home":1806.4,"elo_away":1896.1,"elo_diff":-89.7},"is_frozen":true,"status":"scheduled","home_score":null,"away_score":null}}