{"match_id":"f3d5c28d211183f3","date":"2026-07-11","group":null,"stage":"Quarter-final","home":"Argentina","away":"Switzerland","home_code":"argentina","away_code":"switzerland","status":"played","neutral":true,"city":"Kansas City","country":"United States","home_score":3,"away_score":1,"prediction":{"prediction_id":"22500aeeeca44197","match_id":"f3d5c28d211183f3","model_version_id":"production_ensemble-ac72f6a8e1","data_cutoff":"2026-07-10","created_at":"2026-07-20T15:59:35.679814+00:00","date":"2026-07-11","home_team":"Argentina","away_team":"Switzerland","home_win_probability":0.6333,"draw_probability":0.2851,"away_win_probability":0.0816,"expected_home_goals":1.626,"expected_away_goals":0.873,"expected_total_goals":2.5,"most_likely_score":"1-0","over_2_5":0.4536,"btts_yes":0.4692,"btts_no":0.5308,"over_under":{"0.5":0.9097,"1.5":0.7115,"2.5":0.4536,"3.5":0.2442},"total_goals_dist":[0.0903,0.1982,0.2579,0.2094,0.1317,0.0673,0.0451],"home_clean_sheet":0.4221,"away_clean_sheet":0.199,"home_win_to_nil":0.3318,"away_win_to_nil":0.1087,"top_scorelines":[{"score":"1-0","prob":0.1313},{"score":"1-1","prob":0.1191},{"score":"2-0","prob":0.1084},{"score":"2-1","prob":0.0928},{"score":"0-0","prob":0.0903},{"score":"0-1","prob":0.0669}],"scorers":[],"factors":{"expected_home_goals":1.63,"expected_away_goals":0.87,"neutral_venue":true,"home_is_host":false,"away_is_host":false,"elo_home":2140.3,"elo_away":1938.1,"elo_diff":202.3},"is_frozen":true,"status":"played","home_score":3,"away_score":1}}