{"match_id":"f842c9f7bc590bf3","date":"2026-06-26","group":"H","home":"Uruguay","away":"Spain","status":"scheduled","neutral":true,"city":"Zapopan","country":"Mexico","home_score":null,"away_score":null,"prediction":{"prediction_id":"7d652bcb0a415682","match_id":"f842c9f7bc590bf3","model_version_id":"production_ensemble-a0e241bdc8","data_cutoff":"2026-06-23","created_at":"2026-06-24T10:49:47.300022+00:00","date":"2026-06-26","home_team":"Uruguay","away_team":"Spain","home_win_probability":0.1101,"draw_probability":0.302,"away_win_probability":0.5879,"expected_home_goals":0.751,"expected_away_goals":1.589,"expected_total_goals":2.34,"most_likely_score":"0-1","over_2_5":0.4127,"btts_yes":0.4227,"btts_no":0.5773,"over_under":{"0.5":0.8953,"1.5":0.6774,"2.5":0.4127,"3.5":0.211},"total_goals_dist":[0.1047,0.218,0.2646,0.2017,0.1191,0.0571,0.0349],"home_clean_sheet":0.2083,"away_clean_sheet":0.4736,"home_win_to_nil":0.1036,"away_win_to_nil":0.369,"top_scorelines":[{"score":"0-1","prob":0.1494},{"score":"0-2","prob":0.1198},{"score":"1-1","prob":0.118},{"score":"0-0","prob":0.1047},{"score":"1-2","prob":0.0896},{"score":"1-0","prob":0.0686}],"scorers":[{"player":"Darwin Núñez","team":"Uruguay","prob":0.0959},{"player":"Giorgian de Arrascaeta","team":"Uruguay","prob":0.0939},{"player":"Maximiliano Araújo","team":"Uruguay","prob":0.0811},{"player":"Luis Suárez","team":"Uruguay","prob":0.0725},{"player":"Federico Valverde","team":"Uruguay","prob":0.0584},{"player":"Rodrigo Aguirre","team":"Uruguay","prob":0.0572},{"player":"Agustín Canobbio","team":"Uruguay","prob":0.0385},{"player":"Rodrigo Bentancur","team":"Uruguay","prob":0.0382},{"player":"Nicolás de la Cruz","team":"Uruguay","prob":0.0366},{"player":"Mathías Olivera","team":"Uruguay","prob":0.0277},{"player":"Mikel Oyarzabal","team":"Spain","prob":0.2308},{"player":"Ferran Torres","team":"Spain","prob":0.1593},{"player":"Mikel Merino","team":"Spain","prob":0.151},{"player":"Álvaro Morata","team":"Spain","prob":0.1301},{"player":"Lamine Yamal","team":"Spain","prob":0.0998},{"player":"Dani Olmo","team":"Spain","prob":0.0906},{"player":"Nico Williams","team":"Spain","prob":0.066},{"player":"Joselu","team":"Spain","prob":0.0601},{"player":"Pedri","team":"Spain","prob":0.0511},{"player":"Fabián Ruiz","team":"Spain","prob":0.0511}],"factors":{"expected_home_goals":0.75,"expected_away_goals":1.59,"neutral_venue":true,"home_is_host":false,"away_is_host":false,"elo_home":1895.4,"elo_away":2115.6,"elo_diff":-220.2},"is_frozen":true,"status":"scheduled","home_score":null,"away_score":null}}