{"code":"ecuador","name":"Ecuador","group":"E","confederation":"CONMEBOL","is_host":false,"simulation":{"team":"Ecuador","code":"ecuador","group":"E","confederation":"CONMEBOL","p_win_group":0.0257,"p_runner_up":0.24266666666666667,"p_qualify_third":0.5840333333333333,"p_reach_r32":0.8524,"p_reach_r16":0.4171,"p_reach_qf":0.18053333333333332,"p_reach_sf":0.05293333333333333,"p_reach_final":0.016166666666666666,"p_champion":0.004566666666666667,"se_champion":0.00038926478658372644},"recent_matches":[{"date":"2025-09-09","home":"Ecuador","away":"Argentina","score":"1-0","tournament":"FIFA World Cup qualification"},{"date":"2025-10-10","home":"United States","away":"Ecuador","score":"1-1","tournament":"Friendly"},{"date":"2025-10-14","home":"Mexico","away":"Ecuador","score":"1-1","tournament":"Friendly"},{"date":"2025-11-13","home":"Canada","away":"Ecuador","score":"0-0","tournament":"Friendly"},{"date":"2025-11-18","home":"Ecuador","away":"New Zealand","score":"2-0","tournament":"Friendly"},{"date":"2026-03-27","home":"Morocco","away":"Ecuador","score":"1-1","tournament":"Friendly"},{"date":"2026-03-31","home":"Netherlands","away":"Ecuador","score":"1-1","tournament":"Friendly"},{"date":"2026-05-30","home":"Ecuador","away":"Saudi Arabia","score":"2-1","tournament":"Friendly"},{"date":"2026-06-07","home":"Ecuador","away":"Guatemala","score":"3-0","tournament":"Friendly"},{"date":"2026-06-14","home":"Ivory Coast","away":"Ecuador","score":"1-0","tournament":"FIFA World Cup"}],"group_fixtures":[{"match_id":"677f7fb05eaa9899","date":"2026-06-14","home":"Germany","away":"Curaçao","status":"played","home_score":7,"away_score":1,"p_home":0.9762,"p_draw":0.0205,"p_away":0.0033},{"match_id":"d8eb48a2615d999a","date":"2026-06-14","home":"Ivory Coast","away":"Ecuador","status":"played","home_score":1,"away_score":0,"p_home":0.1484,"p_draw":0.3974,"p_away":0.4542},{"match_id":"9105a1099c143cee","date":"2026-06-20","home":"Germany","away":"Ivory Coast","status":"scheduled","home_score":null,"away_score":null,"p_home":0.6359,"p_draw":0.2773,"p_away":0.0869},{"match_id":"6cf26136d4efb868","date":"2026-06-20","home":"Ecuador","away":"Curaçao","status":"scheduled","home_score":null,"away_score":null,"p_home":0.9151,"p_draw":0.0816,"p_away":0.0033},{"match_id":"6aacb667ee2e6443","date":"2026-06-25","home":"Curaçao","away":"Ivory Coast","status":"scheduled","home_score":null,"away_score":null,"p_home":0.0711,"p_draw":0.162,"p_away":0.7669},{"match_id":"256517dc5075e489","date":"2026-06-25","home":"Ecuador","away":"Germany","status":"scheduled","home_score":null,"away_score":null,"p_home":0.2192,"p_draw":0.3895,"p_away":0.3913}]}